pyscaf/__init__.py
pyscaf/actions/__init__.py
pyscaf/actions/cli_option_to_key.py
pyscaf/actions/core/README.md
pyscaf/actions/core/__init__.py
pyscaf/actions/core/config.toml
pyscaf/actions/core/default_settings.json
pyscaf/actions/documentation/README.md
pyscaf/actions/documentation/__init__.py
pyscaf/actions/documentation/config.toml
pyscaf/actions/documentation/scripts/parse_doc.py
pyscaf/actions/git/README.md
pyscaf/actions/git/__init__.py
pyscaf/actions/git/template.gitignore
pyscaf/actions/jupyter/README.md
pyscaf/actions/jupyter/__init__.py
pyscaf/actions/jupyter/config.toml
pyscaf/actions/jupyter/template.gitignore
pyscaf/actions/jupyter-tools/README.md
pyscaf/actions/jupyter-tools/__init__.py
pyscaf/actions/jupyter-tools/config.toml
pyscaf/actions/jupyter-tools/scripts/execute_notebook.py
pyscaf/actions/jupyter-tools/scripts/main.py
pyscaf/actions/jupyter-tools/scripts/notebook_to_html.py
pyscaf/actions/jupyter-tools/scripts/notebook_to_pdf.py
pyscaf/actions/jupyter-tools/scripts/py_to_notebook.py
pyscaf/actions/jupyter-tools/scripts/shared/exporter.py
pyscaf/actions/license/__init__.py
pyscaf/actions/license/template_Apache-2.0.txt
pyscaf/actions/license/template_BSD-3-Clause.txt
pyscaf/actions/license/template_GPL-3.0.txt
pyscaf/actions/license/template_MIT.txt
pyscaf/actions/license/template_MPL-2.0.txt
pyscaf/actions/license/template_Unlicense.txt
pyscaf/actions/manager.py
pyscaf/actions/semantic-release/README.md
pyscaf/actions/semantic-release/__init__.py
pyscaf/actions/semantic-release/config.toml
pyscaf/actions/semantic-release/github/workflows/deploy-production-manual.yml
pyscaf/actions/semantic-release/github/workflows/release.yml
pyscaf/actions/test/README.md
pyscaf/actions/test/__init__.py
pyscaf/actions/test/config.toml
pyscaf/actions/test/template.gitignore
pyscaf/actions/test/template_test_example.py
pyscaf/cli.py
pyscaf/preference_chain/__init__.py
pyscaf/preference_chain/__main__.py
pyscaf/preference_chain/chain.py
open_pyscaf-1.5.0.dist-info/LICENSE
open_pyscaf-1.5.0.dist-info/METADATA
open_pyscaf-1.5.0.dist-info/WHEEL
open_pyscaf-1.5.0.dist-info/entry_points.txt
open_pyscaf-1.5.0.dist-info/RECORD
