Metadata-Version: 2.3
Name: open-pyscaf
Version: 1.5.0
Summary: A python scaffolder with quarto and other utilities out-of-the-box
License: MIT
Author: guilhem.heinrich
Author-email: guilhem.heinrich@gmail.com
Requires-Python: >=3.10,<4.0
Classifier: License :: OSI Approved :: MIT License
Classifier: Programming Language :: Python :: 3
Classifier: Programming Language :: Python :: 3.10
Classifier: Programming Language :: Python :: 3.11
Classifier: Programming Language :: Python :: 3.12
Classifier: Programming Language :: Python :: 3.13
Requires-Dist: click (>=8.1.0)
Requires-Dist: jinja2 (>=3.0.0)
Requires-Dist: poetry (>=2.1.3,<3.0.0)
Requires-Dist: pydantic (>=2.0.0)
Requires-Dist: questionary (>=2.0.0)
Requires-Dist: rich (>=13.0.0)
Requires-Dist: tomli (>=2.2.1,<3.0.0)
Requires-Dist: tomli-w (>=1.2.0,<2.0.0)
Requires-Dist: tomlkit (>=0.13.3,<0.14.0)
